kagglehelper/__init__.py
kagglehelper/getDataSets.py
kagglehelptool/__init__.py
kagglehelptool/getDataSets.py
kagglefilehelper-0.0.1.dist-info/METADATA
kagglefilehelper-0.0.1.dist-info/WHEEL
kagglefilehelper-0.0.1.dist-info/top_level.txt
kagglefilehelper-0.0.1.dist-info/RECORD
