Metadata-Version: 2.1
Name: kagglefilehelper
Version: 0.0.1
Summary: a pip-installable package kagglefilehelper
Home-page: https://github.com/FatihKaragoz/kagglehelper
Author: Fatih Karagoz
Author-email: fatihkkaragoz@gmail.com
License: MIT
Keywords: kaggle
Platform: UNKNOWN
Classifier: Programming Language :: Python :: 3
Classifier: License :: OSI Approved :: MIT License
Classifier: Operating System :: OS Independent
Requires-Python: >=3.6
Requires-Dist: kagglehub>=0.2.9
